mosestokenizer/__init__.py
mosestokenizer/detokenizer.perl
mosestokenizer/detokenizer.py
mosestokenizer/normalize-punctuation.perl
mosestokenizer/punctnormalizer.py
mosestokenizer/sentsplitter.py
mosestokenizer/split-sentences.perl
mosestokenizer/tokenizer-v1.0.perl
mosestokenizer/tokenizer-v1.1.perl
mosestokenizer/tokenizer.py
mosestokenizer/nonbreaking_prefixes/README.txt
mosestokenizer/nonbreaking_prefixes/nonbreaking_prefix.ca
mosestokenizer/nonbreaking_prefixes/nonbreaking_prefix.cs
mosestokenizer/nonbreaking_prefixes/nonbreaking_prefix.de
mosestokenizer/nonbreaking_prefixes/nonbreaking_prefix.el
mosestokenizer/nonbreaking_prefixes/nonbreaking_prefix.en
mosestokenizer/nonbreaking_prefixes/nonbreaking_prefix.es
mosestokenizer/nonbreaking_prefixes/nonbreaking_prefix.fi
mosestokenizer/nonbreaking_prefixes/nonbreaking_prefix.fr
mosestokenizer/nonbreaking_prefixes/nonbreaking_prefix.hu
mosestokenizer/nonbreaking_prefixes/nonbreaking_prefix.is
mosestokenizer/nonbreaking_prefixes/nonbreaking_prefix.it
mosestokenizer/nonbreaking_prefixes/nonbreaking_prefix.lv
mosestokenizer/nonbreaking_prefixes/nonbreaking_prefix.nl
mosestokenizer/nonbreaking_prefixes/nonbreaking_prefix.pl
mosestokenizer/nonbreaking_prefixes/nonbreaking_prefix.pt
mosestokenizer/nonbreaking_prefixes/nonbreaking_prefix.ro
mosestokenizer/nonbreaking_prefixes/nonbreaking_prefix.ru
mosestokenizer/nonbreaking_prefixes/nonbreaking_prefix.sk
mosestokenizer/nonbreaking_prefixes/nonbreaking_prefix.sl
mosestokenizer/nonbreaking_prefixes/nonbreaking_prefix.sv
mosestokenizer/nonbreaking_prefixes/nonbreaking_prefix.ta
mosestokenizer-1.0.0.dist-info/DESCRIPTION.rst
mosestokenizer-1.0.0.dist-info/METADATA
mosestokenizer-1.0.0.dist-info/RECORD
mosestokenizer-1.0.0.dist-info/WHEEL
mosestokenizer-1.0.0.dist-info/entry_points.txt
mosestokenizer-1.0.0.dist-info/metadata.json
mosestokenizer-1.0.0.dist-info/top_level.txt
