Metadata-Version: 2.0
Name: mosestokenizer
Version: 1.0.0
Summary: Wrappers for several pre-processing scripts from the Moses toolkit.
Home-page: https://bitbucket.org/luismsgomes/mosestokenizer
Author: Luís Gomes
Author-email: luismsgomes@gmail.com
License: LGPLv2
Keywords: text tokenization pre-processing
Platform: UNKNOWN
Classifier: Development Status :: 5 - Production/Stable
Classifier: Intended Audience :: Developers
Classifier: Topic :: Text Processing :: Linguistic
Classifier: License :: OSI Approved :: GNU Lesser General Public License v2 or later (LGPLv2+)
Classifier: Programming Language :: Python :: 3.5
Requires-Dist: docopt
Requires-Dist: openfile
Requires-Dist: toolwrapper
